MANIFEST.in
README.txt
setup.py
cmsplugin_fb_graph/__init__.py
cmsplugin_fb_graph/cms_plugins.py
cmsplugin_fb_graph/models.py
cmsplugin_fb_graph/settings.py
cmsplugin_fb_graph.egg-info/PKG-INFO
cmsplugin_fb_graph.egg-info/SOURCES.txt
cmsplugin_fb_graph.egg-info/dependency_links.txt
cmsplugin_fb_graph.egg-info/entry_points.txt
cmsplugin_fb_graph.egg-info/not-zip-safe
cmsplugin_fb_graph.egg-info/requires.txt
cmsplugin_fb_graph.egg-info/top_level.txt
cmsplugin_fb_graph/migrations/0001_initial.py
cmsplugin_fb_graph/migrations/__init__.py
cmsplugin_fb_graph/templates/cmsplugin_fb_graph/agenda.html
cmsplugin_fb_graph/templates/cmsplugin_fb_graph/news.html
docs/HISTORY.rst
docs/license.txt