Metadata-Version: 1.1
Name: cmsplugin-fb-graph
Version: 0.2
Summary: several django-cms plugins using facebook graph api.
Home-page: http://lagunak.gisa-elkartea.org/projects/cmplugin-fb-graph
Author: GISA Elkartea
Author-email: kontaktua@gisa-elkartea.org
License: GPL
Platform: UNKNOWN
Classifier: Programming Language :: Python
Classifier: Topic :: Software Development :: Libraries :: Python Modules
